{
  "meta": {
    "generatedAt": "2026-04-27T11:31:44.960Z",
    "oraclePath": "D:\\Git\\MTGEDH\\oracle-cards.json",
    "atomicPath": "D:\\Git\\MTGEDH\\AtomicCards.json",
    "includeOracle": true,
    "includeAtomic": false,
    "maxExamples": 5,
    "top": 50
  },
  "stats": {
    "seenUniqueCards": 29800,
    "scannedOracleCards": 29800,
    "scannedAtomicCards": 0,
    "skippedDuplicateOracleId": 0,
    "cardsWithAnyGap": 11316
  },
  "topGaps": [
    {
      "rank": 1,
      "key": "unknown-step|unknown|then you may put a sticker on a nonland permanent you own",
      "raw": "then you may put a sticker on a nonland permanent you own",
      "gapType": "unknown-step",
      "fieldPath": "unknown",
      "count": 24,
      "exampleCards": [
        "Scavenger Hunt",
        "Ambassador Blorpityblorpboop",
        "Aerialephant",
        "Trivia Contest",
        "Glitterflitter"
      ],
      "exampleClauses": [
        "then you may put a sticker on a nonland permanent you own"
      ],
      "sources": {
        "oracle-cards": 24,
        "AtomicCards": 0
      }
    },
    {
      "rank": 2,
      "key": "unknown-step|unknown|you may choose not to untap this creature during your untap step",
      "raw": "You may choose not to untap this creature during your untap step",
      "gapType": "unknown-step",
      "fieldPath": "unknown",
      "count": 16,
      "exampleCards": [
        "Giant Oyster",
        "Frightshroud Courier",
        "Everglove Courier",
        "Sand Squid",
        "Phyrexian Gremlins"
      ],
      "exampleClauses": [
        "You may choose not to untap this creature during your untap step"
      ],
      "sources": {
        "oracle-cards": 16,
        "AtomicCards": 0
      }
    },
    {
      "rank": 3,
      "key": "unknown-step|unknown|this creature loses this ability and becomes an aura enchantment with enchant creature",
      "raw": "This creature loses this ability and becomes an Aura enchantment with enchant creature",
      "gapType": "unknown-step",
      "fieldPath": "unknown",
      "count": 12,
      "exampleCards": [
        "Quickening Licid",
        "Tempting Licid",
        "Transmogrifying Licid",
        "Corrupting Licid",
        "Nurturing Licid"
      ],
      "exampleClauses": [
        "This creature loses this ability and becomes an Aura enchantment with enchant creature"
      ],
      "sources": {
        "oracle-cards": 12,
        "AtomicCards": 0
      }
    },
    {
      "rank": 4,
      "key": "unknown-step|unknown|you may choose not to untap this artifact during your untap step",
      "raw": "You may choose not to untap this artifact during your untap step",
      "gapType": "unknown-step",
      "fieldPath": "unknown",
      "count": 12,
      "exampleCards": [
        "Thran Weaponry",
        "Amber Prison",
        "Helm of Possession",
        "Flowstone Armor",
        "Zelyon Sword"
      ],
      "exampleClauses": [
        "You may choose not to untap this artifact during your untap step"
      ],
      "sources": {
        "oracle-cards": 12,
        "AtomicCards": 0
      }
    },
    {
      "rank": 5,
      "key": "unknown-step|unknown|flip a coin",
      "raw": "Flip a coin",
      "gapType": "unknown-step",
      "fieldPath": "unknown",
      "count": 11,
      "exampleCards": [
        "Polis the Planeshifter",
        "Goblin Lyre",
        "Risky Move",
        "Impulsive Maneuvers",
        "Red and Black Legac"
      ],
      "exampleClauses": [
        "Flip a coin",
        "flip a coin"
      ],
      "sources": {
        "oracle-cards": 11,
        "AtomicCards": 0
      }
    },
    {
      "rank": 6,
      "key": "unknown-step|unknown|instant and sorcery spells you cast cost {1} less to cast",
      "raw": "Instant and sorcery spells you cast cost {1} less to cast",
      "gapType": "unknown-step",
      "fieldPath": "unknown",
      "count": 11,
      "exampleCards": [
        "Mocking Sprite",
        "Storm Skreelix",
        "Jace's Sanctum",
        "Archmage of Runes",
        "Haughty Djinn"
      ],
      "exampleClauses": [
        "Instant and sorcery spells you cast cost {1} less to cast"
      ],
      "sources": {
        "oracle-cards": 11,
        "AtomicCards": 0
      }
    },
    {
      "rank": 7,
      "key": "unknown-step|unknown|then put the rest on the bottom of your library in a random order",
      "raw": "then put the rest on the bottom of your library in a random order",
      "gapType": "unknown-step",
      "fieldPath": "unknown",
      "count": 11,
      "exampleCards": [
        "Glimpse of Tomorrow",
        "Old Stickfingers",
        "Kethek, Crucible Goliath",
        "Sanwell, Avenger Ace",
        "Zimone's Experiment"
      ],
      "exampleClauses": [
        "then put the rest on the bottom of your library in a random order",
        "Then put the rest on the bottom of your library in a random order"
      ],
      "sources": {
        "oracle-cards": 11,
        "AtomicCards": 0
      }
    },
    {
      "rank": 8,
      "key": "unknown-step|unknown|this permanent's power and toughness are each equal to the number of cards in your hand",
      "raw": "this permanent's power and toughness are each equal to the number of cards in your hand",
      "gapType": "unknown-step",
      "fieldPath": "unknown",
      "count": 11,
      "exampleCards": [
        "Duggan, Private Detective",
        "Psychosis Crawler",
        "Kiyomaro, First to Stand",
        "Tishana, Voice of Thunder",
        "Overbeing of Myth"
      ],
      "exampleClauses": [
        "this permanent's power and toughness are each equal to the number of cards in your hand"
      ],
      "sources": {
        "oracle-cards": 11,
        "AtomicCards": 0
      }
    },
    {
      "rank": 9,
      "key": "unknown-step|unknown|all creatures able to block this creature do so",
      "raw": "All creatures able to block this creature do so",
      "gapType": "unknown-step",
      "fieldPath": "unknown",
      "count": 10,
      "exampleCards": [
        "Elvish Bard",
        "Breaker of Armies",
        "Nessian Boar",
        "Nath's Elite",
        "Prized Unicorn"
      ],
      "exampleClauses": [
        "All creatures able to block this creature do so"
      ],
      "sources": {
        "oracle-cards": 10,
        "AtomicCards": 0
      }
    },
    {
      "rank": 10,
      "key": "unknown-step|unknown|cast this spell only during the declare attackers step and only if you've been attacked this step",
      "raw": "Cast this spell only during the declare attackers step and only if you've been attacked this step",
      "gapType": "unknown-step",
      "fieldPath": "unknown",
      "count": 10,
      "exampleCards": [
        "Defiant Stand",
        "Warrior's Stand",
        "Deep Wood",
        "Rally the Troops",
        "Assassin's Blade"
      ],
      "exampleClauses": [
        "Cast this spell only during the declare attackers step and only if you've been attacked this step"
      ],
      "sources": {
        "oracle-cards": 10,
        "AtomicCards": 0
      }
    },
    {
      "rank": 11,
      "key": "unknown-step|unknown|choose one that hasn't been chosen -",
      "raw": "choose one that hasn't been chosen -",
      "gapType": "unknown-step",
      "fieldPath": "unknown",
      "count": 10,
      "exampleCards": [
        "Demonic Pact",
        "Night Out in Vegas",
        "Sol'Kanar the Tainted",
        "Three Bowls of Porridge",
        "Silent Hallcreeper"
      ],
      "exampleClauses": [
        "choose one that hasn't been chosen -",
        "Choose one that hasn't been chosen -"
      ],
      "sources": {
        "oracle-cards": 10,
        "AtomicCards": 0
      }
    },
    {
      "rank": 12,
      "key": "unknown-step|unknown|if you do, this creature assigns no combat damage this turn",
      "raw": "If you do, this creature assigns no combat damage this turn",
      "gapType": "unknown-step",
      "fieldPath": "unknown",
      "count": 10,
      "exampleCards": [
        "Laccolith Titan",
        "Bone Dancer",
        "Kukemssa Pirates",
        "Ophidian",
        "Floral Spuzzem"
      ],
      "exampleClauses": [
        "If you do, this creature assigns no combat damage this turn"
      ],
      "sources": {
        "oracle-cards": 10,
        "AtomicCards": 0
      }
    },
    {
      "rank": 13,
      "key": "unknown-step|unknown|spend this mana only to cast a creature spell",
      "raw": "Spend this mana only to cast a creature spell",
      "gapType": "unknown-step",
      "fieldPath": "unknown",
      "count": 10,
      "exampleCards": [
        "Ancient Ziggurat",
        "Oakhollow Village",
        "Lilypad Village",
        "Herd Heirloom",
        "Rockface Village"
      ],
      "exampleClauses": [
        "Spend this mana only to cast a creature spell"
      ],
      "sources": {
        "oracle-cards": 10,
        "AtomicCards": 0
      }
    },
    {
      "rank": 14,
      "key": "unknown-step|unknown|tapped unless a player has 13 or less life",
      "raw": "tapped unless a player has 13 or less life",
      "gapType": "unknown-step",
      "fieldPath": "unknown",
      "count": 10,
      "exampleCards": [
        "Abandoned Campground",
        "Raucous Carnival",
        "Strangled Cemetery",
        "Bleeding Woods",
        "Etched Cornfield"
      ],
      "exampleClauses": [
        "tapped unless a player has 13 or less life"
      ],
      "sources": {
        "oracle-cards": 10,
        "AtomicCards": 0
      }
    },
    {
      "rank": 15,
      "key": "unknown-step|unknown|tapped unless you control two or more basic lands",
      "raw": "tapped unless you control two or more basic lands",
      "gapType": "unknown-step",
      "fieldPath": "unknown",
      "count": 10,
      "exampleCards": [
        "Sodden Verdure",
        "Smoldering Marsh",
        "Vernal Fen",
        "Prairie Stream",
        "Radiant Summit"
      ],
      "exampleClauses": [
        "tapped unless you control two or more basic lands"
      ],
      "sources": {
        "oracle-cards": 10,
        "AtomicCards": 0
      }
    },
    {
      "rank": 16,
      "key": "unknown-step|unknown|tapped unless you have two or more opponents",
      "raw": "tapped unless you have two or more opponents",
      "gapType": "unknown-step",
      "fieldPath": "unknown",
      "count": 10,
      "exampleCards": [
        "Spire Garden",
        "Sea of Clouds",
        "Bountiful Promenade",
        "Undergrowth Stadium",
        "Luxury Suite"
      ],
      "exampleClauses": [
        "tapped unless you have two or more opponents"
      ],
      "sources": {
        "oracle-cards": 10,
        "AtomicCards": 0
      }
    },
    {
      "rank": 17,
      "key": "unknown-step|unknown|the next time a source of your choice would deal damage to you this turn, prevent that damage",
      "raw": "The next time a source of your choice would deal damage to you this turn, prevent that damage",
      "gapType": "unknown-step",
      "fieldPath": "unknown",
      "count": 10,
      "exampleCards": [
        "Cho-Arrim Alchemist",
        "Invulnerability",
        "New Way Forward",
        "Haazda Shield Mate",
        "Righteous Aura"
      ],
      "exampleClauses": [
        "The next time a source of your choice would deal damage to you this turn, prevent that damage"
      ],
      "sources": {
        "oracle-cards": 10,
        "AtomicCards": 0
      }
    },
    {
      "rank": 18,
      "key": "unknown-fragment|deal_damage.amount|the sacrificed creature's power",
      "raw": "the sacrificed creature's power",
      "gapType": "unknown-fragment",
      "fieldPath": "deal_damage.amount",
      "count": 10,
      "exampleCards": [
        "Fling",
        "Airdrop Condor",
        "Rite of Consumption",
        "Wick, the Whorled Mind",
        "Thud"
      ],
      "exampleClauses": [
        "this permanent deals damage equal to the sacrificed creature's power to any target",
        "This creature deals damage equal to the sacrificed creature's power to any target",
        "this permanent deals damage equal to the sacrificed creature's power to target player or planeswalker",
        "this permanent deals damage equal to the sacrificed creature's power to each opponent",
        "This Aura deals damage equal to the sacrificed creature's power to each creature"
      ],
      "sources": {
        "oracle-cards": 10,
        "AtomicCards": 0
      }
    },
    {
      "rank": 19,
      "key": "unknown-step|unknown|then you may put that card on the bottom.)",
      "raw": "then you may put that card on the bottom.)",
      "gapType": "unknown-step",
      "fieldPath": "unknown",
      "count": 10,
      "exampleCards": [
        "Eager Construct",
        "Oracle's Insight",
        "Battlewise Hoplite",
        "Chorus of the Tides",
        "Artificer's Assistant"
      ],
      "exampleClauses": [
        "then you may put that card on the bottom.)"
      ],
      "sources": {
        "oracle-cards": 10,
        "AtomicCards": 0
      }
    },
    {
      "rank": 20,
      "key": "unknown-step|unknown|this permanent's power and toughness are each equal to the number of creatures you control",
      "raw": "this permanent's power and toughness are each equal to the number of creatures you control",
      "gapType": "unknown-step",
      "fieldPath": "unknown",
      "count": 10,
      "exampleCards": [
        "Battle Squadron",
        "Seraph of the Masses",
        "Queen Allenal of Ruadach",
        "Veteran Warleader",
        "Scion of the Wild"
      ],
      "exampleClauses": [
        "this permanent's power and toughness are each equal to the number of creatures you control"
      ],
      "sources": {
        "oracle-cards": 10,
        "AtomicCards": 0
      }
    },
    {
      "rank": 21,
      "key": "unknown-step|unknown|this permanent's power is equal to the number of creatures you control",
      "raw": "this permanent's power is equal to the number of creatures you control",
      "gapType": "unknown-step",
      "fieldPath": "unknown",
      "count": 10,
      "exampleCards": [
        "Snow Villiers",
        "Kolaghan Forerunners",
        "Sumala Rumblers",
        "Freedom Fighter Recruit",
        "Adeline, Resplendent Cathar"
      ],
      "exampleClauses": [
        "this permanent's power is equal to the number of creatures you control"
      ],
      "sources": {
        "oracle-cards": 10,
        "AtomicCards": 0
      }
    },
    {
      "rank": 22,
      "key": "unknown-step|unknown|you get {tk}",
      "raw": "you get {TK}",
      "gapType": "unknown-step",
      "fieldPath": "unknown",
      "count": 10,
      "exampleCards": [
        "Park Bleater",
        "Aerialephant",
        "Glitterflitter",
        "Prize Wall",
        "Scampire"
      ],
      "exampleClauses": [
        "you get {TK}",
        "You get {TK}"
      ],
      "sources": {
        "oracle-cards": 10,
        "AtomicCards": 0
      }
    },
    {
      "rank": 23,
      "key": "unknown-step|unknown|you may cast the copy without paying its mana cost",
      "raw": "You may cast the copy without paying its mana cost",
      "gapType": "unknown-step",
      "fieldPath": "unknown",
      "count": 10,
      "exampleCards": [
        "Chandra's Dragonmech",
        "Spellweaver Volute",
        "Mysterious Stranger",
        "Myra the Magnificent",
        "Surge to Victory"
      ],
      "exampleClauses": [
        "You may cast the copy without paying its mana cost"
      ],
      "sources": {
        "oracle-cards": 10,
        "AtomicCards": 0
      }
    },
    {
      "rank": 24,
      "key": "unknown-step|unknown|you may put a name sticker on it",
      "raw": "you may put a name sticker on it",
      "gapType": "unknown-step",
      "fieldPath": "unknown",
      "count": 10,
      "exampleCards": [
        "_____ Bird Gets the Worm",
        "_____-o-saurus",
        "Last Voyage of the _____",
        "Wolf in _____ Clothing",
        "Fight the _____ Fight"
      ],
      "exampleClauses": [
        "you may put a name sticker on it"
      ],
      "sources": {
        "oracle-cards": 10,
        "AtomicCards": 0
      }
    },
    {
      "rank": 25,
      "key": "unknown-step|unknown|you may tap a creature you control to reduce that cost by {x}, where x is its power",
      "raw": "You may tap a creature you control to reduce that cost by {X}, where X is its power",
      "gapType": "unknown-step",
      "fieldPath": "unknown",
      "count": 10,
      "exampleCards": [
        "Songcrafter Mage",
        "Wild Ride",
        "Mammoth Bellow",
        "Glacial Dragonhunt",
        "Channeled Dragonfire"
      ],
      "exampleClauses": [
        "You may tap a creature you control to reduce that cost by {X}, where X is its power"
      ],
      "sources": {
        "oracle-cards": 10,
        "AtomicCards": 0
      }
    },
    {
      "rank": 26,
      "key": "unknown-step|unknown|activate only if creatures you control have total power 8 or greater",
      "raw": "Activate only if creatures you control have total power 8 or greater",
      "gapType": "unknown-step",
      "fieldPath": "unknown",
      "count": 9,
      "exampleCards": [
        "Dragon-Scarred Bear",
        "Atarka Pummeler",
        "Dragon Whisperer",
        "Lurking Arynx",
        "Crater Elemental"
      ],
      "exampleClauses": [
        "Activate only if creatures you control have total power 8 or greater"
      ],
      "sources": {
        "oracle-cards": 9,
        "AtomicCards": 0
      }
    },
    {
      "rank": 27,
      "key": "unknown-step|unknown|damage can't be prevented this turn",
      "raw": "Damage can't be prevented this turn",
      "gapType": "unknown-step",
      "fieldPath": "unknown",
      "count": 9,
      "exampleCards": [
        "Math is for Blockers",
        "Isengard Unleashed",
        "Fear, Fire, Foes!",
        "Skullcrack",
        "Pyrewood Gearhulk"
      ],
      "exampleClauses": [
        "Damage can't be prevented this turn"
      ],
      "sources": {
        "oracle-cards": 9,
        "AtomicCards": 0
      }
    },
    {
      "rank": 28,
      "key": "unknown-step|unknown|discard any number of cards",
      "raw": "discard any number of cards",
      "gapType": "unknown-step",
      "fieldPath": "unknown",
      "count": 9,
      "exampleCards": [
        "Colossus of the Blood Age",
        "Last Rites",
        "Into the Night",
        "Sacred Rites",
        "Cavalier of Flame"
      ],
      "exampleClauses": [
        "discard any number of cards",
        "Discard any number of cards"
      ],
      "sources": {
        "oracle-cards": 9,
        "AtomicCards": 0
      }
    },
    {
      "rank": 29,
      "key": "unknown-step|unknown|each creature you control with a +1/+1 counter on it has trample",
      "raw": "Each creature you control with a +1/+1 counter on it has trample",
      "gapType": "unknown-step",
      "fieldPath": "unknown",
      "count": 9,
      "exampleCards": [
        "Zegana, Utopian Speaker",
        "Drix Fatemaker",
        "Crowned Ceratok",
        "Tuskguard Captain",
        "Bramblewood Paragon"
      ],
      "exampleClauses": [
        "Each creature you control with a +1/+1 counter on it has trample"
      ],
      "sources": {
        "oracle-cards": 9,
        "AtomicCards": 0
      }
    },
    {
      "rank": 30,
      "key": "unknown-step|unknown|he enters tapped and attacking.)",
      "raw": "He enters tapped and attacking.)",
      "gapType": "unknown-step",
      "fieldPath": "unknown",
      "count": 9,
      "exampleCards": [
        "Michelangelo, Improviser",
        "Leonardo, Leader in Blue",
        "Splinter, Hamato Yoshi",
        "Shredder, Unrelenting",
        "Leonardo, Big Brother"
      ],
      "exampleClauses": [
        "He enters tapped and attacking.)"
      ],
      "sources": {
        "oracle-cards": 9,
        "AtomicCards": 0
      }
    },
    {
      "rank": 31,
      "key": "unknown-step|unknown|if you cast it any time a sorcery couldn't have been cast, the controller of the permanent it becomes sacrifices it at the beginning of the next cleanup step",
      "raw": "If you cast it any time a sorcery couldn't have been cast, the controller of the permanent it becomes sacrifices it at the beginning of the next cleanup step",
      "gapType": "unknown-step",
      "fieldPath": "unknown",
      "count": 9,
      "exampleCards": [
        "Spider Climb",
        "Lightning Reflexes",
        "Mystic Veil",
        "Parapet",
        "Necromancy"
      ],
      "exampleClauses": [
        "If you cast it any time a sorcery couldn't have been cast, the controller of the permanent it becomes sacrifices it at the beginning of the next cleanup step"
      ],
      "sources": {
        "oracle-cards": 9,
        "AtomicCards": 0
      }
    },
    {
      "rank": 32,
      "key": "unknown-step|unknown|put its counters on target creature you control",
      "raw": "put its counters on target creature you control",
      "gapType": "unknown-step",
      "fieldPath": "unknown",
      "count": 9,
      "exampleCards": [
        "Essence Channeler",
        "Star Pupil",
        "Spiteful Squad",
        "Sin, Unending Cataclysm",
        "Hei Bai, Spirit of Balance"
      ],
      "exampleClauses": [
        "put its counters on target creature you control"
      ],
      "sources": {
        "oracle-cards": 9,
        "AtomicCards": 0
      }
    },
    {
      "rank": 33,
      "key": "unknown-step|unknown|reveal those cards, put them into your hand",
      "raw": "Reveal those cards, put them into your hand",
      "gapType": "unknown-step",
      "fieldPath": "unknown",
      "count": 9,
      "exampleCards": [
        "Prismatic Undercurrents",
        "Tithe",
        "Conflux",
        "Nissa's Encouragement",
        "Gem of Becoming"
      ],
      "exampleClauses": [
        "Reveal those cards, put them into your hand"
      ],
      "sources": {
        "oracle-cards": 9,
        "AtomicCards": 0
      }
    },
    {
      "rank": 34,
      "key": "unknown-step|unknown|target creature blocks this creature this turn if able",
      "raw": "Target creature blocks this creature this turn if able",
      "gapType": "unknown-step",
      "fieldPath": "unknown",
      "count": 9,
      "exampleCards": [
        "Vortex Elemental",
        "Lurking Arynx",
        "Maraleaf Rider",
        "Torchling",
        "Trumpeting Armodon"
      ],
      "exampleClauses": [
        "Target creature blocks this creature this turn if able"
      ],
      "sources": {
        "oracle-cards": 9,
        "AtomicCards": 0
      }
    },
    {
      "rank": 35,
      "key": "unknown-step|unknown|that many plus one +1/+1 counters are put on it",
      "raw": "that many plus one +1/+1 counters are put on it",
      "gapType": "unknown-step",
      "fieldPath": "unknown",
      "count": 9,
      "exampleCards": [
        "Benevolent Hydra",
        "Michelangelo, Weirdness to 11",
        "Mowu, Loyal Companion",
        "Ozolith, the Shattered Spire",
        "Zabaz, the Glimmerwasp"
      ],
      "exampleClauses": [
        "that many plus one +1/+1 counters are put on it"
      ],
      "sources": {
        "oracle-cards": 9,
        "AtomicCards": 0
      }
    },
    {
      "rank": 36,
      "key": "unknown-fragment|impulse_exile_top.amount|until you exile a nonland card with mana value 4 or less",
      "raw": "until you exile a nonland card with mana value 4 or less",
      "gapType": "unknown-fragment",
      "fieldPath": "impulse_exile_top.amount",
      "count": 9,
      "exampleCards": [
        "Hidden Nursery",
        "Long-Range Sensor",
        "Quintorius Kand",
        "Hidden Cataract",
        "Hidden Volcano"
      ],
      "exampleClauses": [
        "Exile cards from the top of your library until you exile a nonland card with mana value 4 or less. You may cast that card without paying its mana cost. Put the remaining exiled cards on the bottom of your library in a random order."
      ],
      "sources": {
        "oracle-cards": 9,
        "AtomicCards": 0
      }
    },
    {
      "rank": 37,
      "key": "unknown-step|unknown|ward-discard a card",
      "raw": "Ward-Discard a card",
      "gapType": "unknown-step",
      "fieldPath": "unknown",
      "count": 9,
      "exampleCards": [
        "Mighty Servant of Leuk-o",
        "Tragedy Feaster",
        "Maha, Its Feathers Night",
        "Westgate Regent",
        "Spectral Snatcher"
      ],
      "exampleClauses": [
        "Ward-Discard a card"
      ],
      "sources": {
        "oracle-cards": 9,
        "AtomicCards": 0
      }
    },
    {
      "rank": 38,
      "key": "unknown-fragment|create_token.amount|with",
      "raw": "with",
      "gapType": "unknown-fragment",
      "fieldPath": "create_token.amount",
      "count": 9,
      "exampleCards": [
        "The Girl in the Fireplace",
        "Teferi, Temporal Pilgrim",
        "Ashiok, Wicked Manipulator",
        "Mascot Exhibition",
        "Fugitive of the Judoon"
      ],
      "exampleClauses": [
        "I - Create a 1/1 white Human Noble creature token with vanishing 3 and \"Prevent all damage that would be dealt to this token.\"",
        "Create a 2/2 blue Spirit creature token with vigilance and \"Whenever you draw a card, put a +1/+1 counter on this token.\"",
        "Create two 1/1 black Nightmare creature tokens with \"At the beginning of combat on your turn, if a card was put into exile this turn, put a +1/+1 counter on this token.\"",
        "Create a 2/1 white and black Inkling creature token with flying, a 3/2 red and white Spirit creature token, and a 4/4 blue and red Elemental creature token",
        "I - Create a 1/1 white Human creature token with ward {2} and a 4/4 white Alien Rhino creature token"
      ],
      "sources": {
        "oracle-cards": 9,
        "AtomicCards": 0
      }
    },
    {
      "rank": 39,
      "key": "unknown-step|unknown|you may cast this spell as though it had flash",
      "raw": "You may cast this spell as though it had flash",
      "gapType": "unknown-step",
      "fieldPath": "unknown",
      "count": 9,
      "exampleCards": [
        "Spider Climb",
        "Lightning Reflexes",
        "Mystic Veil",
        "Parapet",
        "Necromancy"
      ],
      "exampleClauses": [
        "You may cast this spell as though it had flash"
      ],
      "sources": {
        "oracle-cards": 9,
        "AtomicCards": 0
      }
    },
    {
      "rank": 40,
      "key": "unknown-step|unknown|4/4",
      "raw": "4/4",
      "gapType": "unknown-step",
      "fieldPath": "unknown",
      "count": 8,
      "exampleCards": [
        "Student of Warfare",
        "Coralhelm Commander",
        "Knight of Cliffhaven",
        "Hexdrinker",
        "Beastbreaker of Bala Ged"
      ],
      "exampleClauses": [
        "4/4"
      ],
      "sources": {
        "oracle-cards": 8,
        "AtomicCards": 0
      }
    },
    {
      "rank": 41,
      "key": "unknown-step|unknown|add one mana of any color in your commander's color identity",
      "raw": "Add one mana of any color in your commander's color identity",
      "gapType": "unknown-step",
      "fieldPath": "unknown",
      "count": 8,
      "exampleCards": [
        "Command Mine",
        "Command Tower",
        "Commander's Sphere",
        "Arcane Signet",
        "Opal Palace"
      ],
      "exampleClauses": [
        "Add one mana of any color in your commander's color identity"
      ],
      "sources": {
        "oracle-cards": 8,
        "AtomicCards": 0
      }
    },
    {
      "rank": 42,
      "key": "unknown-step|unknown|an opponent chooses one of those piles",
      "raw": "An opponent chooses one of those piles",
      "gapType": "unknown-step",
      "fieldPath": "unknown",
      "count": 8,
      "exampleCards": [
        "Steam Augury",
        "Truth or Tale",
        "Epiphany at the Drownyard",
        "Abstract Performance",
        "Split the Spoils"
      ],
      "exampleClauses": [
        "An opponent chooses one of those piles"
      ],
      "sources": {
        "oracle-cards": 8,
        "AtomicCards": 0
      }
    },
    {
      "rank": 43,
      "key": "unknown-step|unknown|choose a nonland card name",
      "raw": "Choose a nonland card name",
      "gapType": "unknown-step",
      "fieldPath": "unknown",
      "count": 8,
      "exampleCards": [
        "Cabal Therapy",
        "Stain the Mind",
        "Cranial Extraction",
        "Thought Hemorrhage",
        "Tamiyo, Collector of Tales"
      ],
      "exampleClauses": [
        "Choose a nonland card name"
      ],
      "sources": {
        "oracle-cards": 8,
        "AtomicCards": 0
      }
    },
    {
      "rank": 44,
      "key": "unknown-step|unknown|choose one",
      "raw": "Choose one",
      "gapType": "unknown-step",
      "fieldPath": "unknown",
      "count": 8,
      "exampleCards": [
        "Aetheric Amplifier",
        "Moxite Refinery",
        "Wild Shape",
        "Gnostro, Voice of the Crags",
        "Skinshifter"
      ],
      "exampleClauses": [
        "Choose one"
      ],
      "sources": {
        "oracle-cards": 8,
        "AtomicCards": 0
      }
    },
    {
      "rank": 45,
      "key": "unknown-step|unknown|creatures with power less than this creature's power can't block it",
      "raw": "Creatures with power less than this creature's power can't block it",
      "gapType": "unknown-step",
      "fieldPath": "unknown",
      "count": 8,
      "exampleCards": [
        "Wandering Wolf",
        "Aura Gnarlid",
        "Den Protector",
        "Howlgeist",
        "Formation Breaker"
      ],
      "exampleClauses": [
        "Creatures with power less than this creature's power can't block it"
      ],
      "sources": {
        "oracle-cards": 8,
        "AtomicCards": 0
      }
    },
    {
      "rank": 46,
      "key": "unknown-step|unknown|each player shuffles their hand and graveyard into their library",
      "raw": "Each player shuffles their hand and graveyard into their library",
      "gapType": "unknown-step",
      "fieldPath": "unknown",
      "count": 8,
      "exampleCards": [
        "Game Plan",
        "Echo of Eons",
        "Jace, the Living Guildpact",
        "Day's Undoing",
        "Emergency Powers"
      ],
      "exampleClauses": [
        "Each player shuffles their hand and graveyard into their library"
      ],
      "sources": {
        "oracle-cards": 8,
        "AtomicCards": 0
      }
    },
    {
      "rank": 47,
      "key": "unknown-fragment|modify_pt.scaler|for each creature blocking it",
      "raw": "for each creature blocking it",
      "gapType": "unknown-fragment",
      "fieldPath": "modify_pt.scaler",
      "count": 8,
      "exampleCards": [
        "Rabid Elephant",
        "Berserk Murlodont",
        "Gang of Elk",
        "Sparring Golem",
        "Elvish Berserker"
      ],
      "exampleClauses": [
        "it gets +2/+2 until end of turn for each creature blocking it",
        "it gets +1/+1 until end of turn for each creature blocking it",
        "it gets +3/+3 until end of turn for each creature blocking it"
      ],
      "sources": {
        "oracle-cards": 8,
        "AtomicCards": 0
      }
    },
    {
      "rank": 48,
      "key": "unknown-step|unknown|if damage would be dealt to this creature, prevent that damage",
      "raw": "If damage would be dealt to this creature, prevent that damage",
      "gapType": "unknown-step",
      "fieldPath": "unknown",
      "count": 8,
      "exampleCards": [
        "Phantom Nantuko",
        "Phantom Tiger",
        "Phyrexian Vindicator",
        "Phantom Centaur",
        "Phantom Wurm"
      ],
      "exampleClauses": [
        "If damage would be dealt to this creature, prevent that damage"
      ],
      "sources": {
        "oracle-cards": 8,
        "AtomicCards": 0
      }
    },
    {
      "rank": 49,
      "key": "unknown-step|unknown|if its toughness is 0 or less, it still dies.)",
      "raw": "If its toughness is 0 or less, it still dies.)",
      "gapType": "unknown-step",
      "fieldPath": "unknown",
      "count": 8,
      "exampleCards": [
        "Iron-Shield Elf",
        "Pitiless Vizier",
        "Gilt-Leaf's Embrace",
        "Burdened Stoneback",
        "Accursed Horde"
      ],
      "exampleClauses": [
        "If its toughness is 0 or less, it still dies.)"
      ],
      "sources": {
        "oracle-cards": 8,
        "AtomicCards": 0
      }
    },
    {
      "rank": 50,
      "key": "unknown-step|unknown|if you do, choose an opponent to also copy it",
      "raw": "If you do, choose an opponent to also copy it",
      "gapType": "unknown-step",
      "fieldPath": "unknown",
      "count": 8,
      "exampleCards": [
        "Replication Technique",
        "Try-My-Deck Elemental",
        "Healing Technique",
        "The Sixth Seraph",
        "The Twelfth Doctor"
      ],
      "exampleClauses": [
        "If you do, choose an opponent to also copy it"
      ],
      "sources": {
        "oracle-cards": 8,
        "AtomicCards": 0
      }
    }
  ]
}